async_mc_launcher_core-0.4.dist-info/licenses/LICENSE
launcher_core/CustomClass.py
launcher_core/__init__.py
launcher_core/_helper.py
launcher_core/check_version.py
launcher_core/command.py
launcher_core/exceptions.py
launcher_core/fabric.py
launcher_core/forge.py
launcher_core/http_client.py
launcher_core/install.py
launcher_core/java_utils.py
launcher_core/logging_utils.py
launcher_core/microsoft_account.py
launcher_core/microsoft_types.py
launcher_core/mojang.py
launcher_core/mrpack.py
launcher_core/natives.py
launcher_core/news.py
launcher_core/quilt.py
launcher_core/runtime.py
launcher_core/setting.py
launcher_core/utils.py
launcher_core/_internal_types/__init__.py
launcher_core/_internal_types/forge_types.py
launcher_core/_internal_types/helper_types.py
launcher_core/_internal_types/install_types.py
launcher_core/_internal_types/mrpack_types.py
launcher_core/_internal_types/runtime_types.py
launcher_core/_internal_types/shared_types.py
launcher_core/_internal_types/vanilla_launcher_types.py
launcher_core/config/__init__.py
launcher_core/config/load_launcher_config.py
launcher_core/config/vanilla_profile.py
launcher_core/models/__init__.py
launcher_core/models/auth.py
launcher_core/models/downloads.py
launcher_core/models/java.py
launcher_core/models/launcher.py
launcher_core/models/minecraft.py
launcher_core/models/modding.py
launcher_core/models/mojang.py
launcher_core/models/news.py
launcher_core/models/profiles.py
launcher_core/models/runtime.py
launcher_core/models/server.py
async_mc_launcher_core-0.4.dist-info/METADATA
async_mc_launcher_core-0.4.dist-info/WHEEL
async_mc_launcher_core-0.4.dist-info/top_level.txt
async_mc_launcher_core-0.4.dist-info/RECORD
