Metadata-Version: 2.4
Name: async-mc-launcher-core
Version: 0.4
Summary: A Modern Async Python Library for Minecraft Launcher Development
Author-email: JaydenChao101 <jaydenchao@proton.me>
License-Expression: BSD-2-Clause
Project-URL: Issues, https://github.com/JaydenChao101/async-mc-launcher-core/issues
Project-URL: Source, https://github.com/JaydenChao101/async-mc-launcher-core
Keywords: Minecraft,Mojang,launcher,minecraft-launcher,java,async
Classifier: Development Status :: 5 - Production/Stable
Classifier: Intended Audience :: Developers
Classifier: Intended Audience :: End Users/Desktop
Classifier: Topic :: Games/Entertainment
Classifier: Topic :: Software Development :: Libraries :: Python Modules
Classifier: Programming Language :: Python :: 3.10
Classifier: Programming Language :: Python :: 3.11
Classifier: Programming Language :: Python :: 3.12
Classifier: Programming Language :: Python :: 3.13
Classifier: Programming Language :: Python :: Implementation :: CPython
Classifier: Programming Language :: Python :: Implementation :: PyPy
Classifier: Typing :: Typed
Classifier: Operating System :: OS Independent
Classifier: Framework :: AsyncIO
Requires-Python: >=3.10
License-File: LICENSE
Requires-Dist: aiofiles>=24.1.0
Requires-Dist: aiohttp>=3.12.14
Requires-Dist: cryptography>=45.0.2
Requires-Dist: flake8>=7.3.0
Requires-Dist: pydantic>=2.11.7
Requires-Dist: pydantic-settings>=2.7.0
Requires-Dist: pyjwt>=2.10.1
Requires-Dist: tomli>=1.2.0; python_version < "3.11"
Requires-Dist: tomli-w>=1.2.0
Dynamic: license-file
